tests/__init__.py
tests/test_core.py
textutils/__init__.py
textutils/core.py
my_textutils-0.1.2.dist-info/LICENSE
my_textutils-0.1.2.dist-info/METADATA
my_textutils-0.1.2.dist-info/WHEEL
my_textutils-0.1.2.dist-info/top_level.txt
my_textutils-0.1.2.dist-info/RECORD
